grpc_route/__init__.py
grpc_route/client.py
grpc_route/client0.py
grpc_route/error.py
grpc_route/server.py
grpc_route/server0.py
grpc_route/utils.py
grpc_route/wrap.py
grpc_route/core/__init__.py
grpc_route/core/_compat.py
grpc_route/core/app.py
grpc_route/core/common.py
grpc_route/core/ctx.py
grpc_route/core/error.py
grpc_route/core/globals.py
grpc_route/core/local.py
grpc_route/core/logging.py
grpc_route/core/response.py
grpc_route-0.1.2.20010521.dist-info/LICENSE
grpc_route-0.1.2.20010521.dist-info/METADATA
grpc_route-0.1.2.20010521.dist-info/WHEEL
grpc_route-0.1.2.20010521.dist-info/top_level.txt
grpc_route-0.1.2.20010521.dist-info/RECORD
