Metadata-Version: 2.1
Name: grpc-route
Version: 0.1.2.20010521
Summary: Python gRPC 回调方式实现CS通讯（类flask）
Home-page: https://github.com/BingerYang/grpc_route
Author: binger
Author-email: <xuehen_521@126.com>
Maintainer: binger
Maintainer-email: <xuehen_521@126.com>
License: UNKNOWN
Platform: all
Requires-Python: >=3.4
